convertimage/__init__.py
convertimage/convertexcel.py
convertimage/convertimage.py
convertimage/convertword.py
pdfconverter/__init__.py
pdfconverter/convertexcel.py
pdfconverter/convertimage.py
pdfconverter/convertword.py
pdfconverter/pdfconverter.py
pdfconverter-1.0.1.dist-info/METADATA
pdfconverter-1.0.1.dist-info/WHEEL
pdfconverter-1.0.1.dist-info/entry_points.txt
pdfconverter-1.0.1.dist-info/top_level.txt
pdfconverter-1.0.1.dist-info/RECORD
