Metadata-Version: 2.1
Name: pdfconverter
Version: 1.0.1
Summary: Python command line program for converting different files to pdfs
Home-page: https://github.com/HermitOS/pdfconverter/tree/main/package
Author: Isabel Sandstrøm
Author-email: isabel@hermit.no
License: UNKNOWN
Platform: UNKNOWN
Classifier: Programming Language :: Python :: 3
Classifier: License :: OSI Approved :: MIT License
Classifier: Operating System :: OS Independent
Requires-Python: >=3.6
Requires-Dist: fpdf (>=1.7.2)
Requires-Dist: pywin32 (>=303)
Requires-Dist: pywin32-ctypes (>=0.2.0)
Requires-Dist: Pillow (>=8.4.0)
